LICENSE
wagtailpress/__init__.py
wagtailpress/admin.py
wagtailpress/apps.py
wagtailpress/blocks.py
wagtailpress/locale/fr/LC_MESSAGES/django.mo
wagtailpress/locale/fr/LC_MESSAGES/django.po
wagtailpress/locale/fr/LC_MESSAGES/django.po~
wagtailpress/migrations/0001_initial.py
wagtailpress/migrations/0002_auto_20190827_1629.py
wagtailpress/migrations/0003_auto_20190827_1725.py
wagtailpress/migrations/0004_auto_20190827_1800.py
wagtailpress/migrations/0005_blogindexpage.py
wagtailpress/migrations/0006_auto_20190828_1515.py
wagtailpress/migrations/0007_auto_20190905_1332.py
wagtailpress/migrations/0008_auto_20191001_1317.py
wagtailpress/migrations/0009_auto_20200415_1507.py
wagtailpress/migrations/0010_alter_blogarticleauthor_author_and_more.py
wagtailpress/migrations/__init__.py
wagtailpress/models.py
wagtailpress/static/wagtailpress/Fork-Awesome/.all-contributorsrc
wagtailpress/static/wagtailpress/Fork-Awesome/.github/ISSUE_TEMPLATE/Icon_request.md
wagtailpress/static/wagtailpress/Fork-Awesome/.gitignore
wagtailpress/static/wagtailpress/Fork-Awesome/.npmignore
wagtailpress/static/wagtailpress/Fork-Awesome/.travis.yml
wagtailpress/static/wagtailpress/Fork-Awesome/CHANGELOG.md
wagtailpress/static/wagtailpress/Fork-Awesome/CONTRIBUTING.md
wagtailpress/static/wagtailpress/Fork-Awesome/CONTRIBUTORS.md
wagtailpress/static/wagtailpress/Fork-Awesome/Gemfile
wagtailpress/static/wagtailpress/Fork-Awesome/Gemfile.lock
wagtailpress/static/wagtailpress/Fork-Awesome/LICENSES
wagtailpress/static/wagtailpress/Fork-Awesome/README.md
wagtailpress/static/wagtailpress/Fork-Awesome/_config-deploy.yml
wagtailpress/static/wagtailpress/Fork-Awesome/_config.yml
wagtailpress/static/wagtailpress/Fork-Awesome/bower.json
wagtailpress/static/wagtailpress/Fork-Awesome/component.json
wagtailpress/static/wagtailpress/Fork-Awesome/composer.json
wagtailpress/static/wagtailpress/Fork-Awesome/css/fork-awesome.css
wagtailpress/static/wagtailpress/Fork-Awesome/css/fork-awesome.min.css
wagtailpress-0.13.0.dist-info/LICENSE
wagtailpress-0.13.0.dist-info/WHEEL
wagtailpress-0.13.0.dist-info/METADATA
wagtailpress-0.13.0.dist-info/RECORD
