Metadata-Version: 2.1
Name: wagtailpress
Version: 0.13.0
Summary: A Blog build with Wagtail.
Home-page: https://framagit.org/SebGen/wagtailpress
License: LGPL-3.0-only
Keywords: wagtailperson,wagtail,person
Author: Sébastien Gendre
Author-email: seb@k-7.ch
Requires-Python: >=3.9,<4.0
Classifier: Development Status :: 4 - Beta
Classifier: Framework :: Django
Classifier: Framework :: Wagtail
Classifier: Framework :: Wagtail :: 2
Classifier: License :: OSI Approved :: GNU Lesser General Public License v3 (LGPLv3)
Classifier: Operating System :: OS Independent
Classifier: Programming Language :: Python
Classifier: Programming Language :: Python :: 3
Classifier: Programming Language :: Python :: 3.10
Classifier: Programming Language :: Python :: 3.9
Classifier: Topic :: Internet
Classifier: Topic :: Software Development :: Libraries :: Python Modules
Requires-Dist: wagtail (>=4.2,<5.0)
Requires-Dist: wagtailperson (>=0.14,<0.15)
Project-URL: Repository, https://framagit.org/SebGen/wagtailpress
